cisco_gnmi/__init__.py
cisco_gnmi/auth.py
cisco_gnmi/builder.py
cisco_gnmi/cli.py
cisco_gnmi/client.py
cisco_gnmi/nx.py
cisco_gnmi/util.py
cisco_gnmi/xe.py
cisco_gnmi/xr.py
cisco_gnmi/proto/__init__.py
cisco_gnmi/proto/gnmi_ext_pb2.py
cisco_gnmi/proto/gnmi_ext_pb2_grpc.py
cisco_gnmi/proto/gnmi_pb2.py
cisco_gnmi/proto/gnmi_pb2_grpc.py
cisco_gnmi-1.0.16.dist-info/LICENSE
cisco_gnmi-1.0.16.dist-info/METADATA
cisco_gnmi-1.0.16.dist-info/NOTICE
cisco_gnmi-1.0.16.dist-info/WHEEL
cisco_gnmi-1.0.16.dist-info/entry_points.txt
cisco_gnmi-1.0.16.dist-info/top_level.txt
cisco_gnmi-1.0.16.dist-info/RECORD
