Metadata-Version: 2.1
Name: cisco-gnmi
Version: 1.0.16
Summary: This library wraps gNMI functionality to ease usage with Cisco implementations.
Home-page: https://github.com/cisco-ie/cisco-gnmi-python
Author: Cisco Innovation Edge
Author-email: cisco-ie@cisco.com
Maintainer: Cisco Innovation Edge
Maintainer-email: cisco-ie@cisco.com
License: Apache License (2.0)
Project-URL: Code, https://github.com/cisco-ie/cisco-gnmi-python
Project-URL: Issue Tracker, https://github.com/cisco-ie/cisco-gnmi-python/issues
Classifier: Development Status :: 5 - Production/Stable
Classifier: Topic :: System :: Networking
Classifier: Topic :: System :: Networking :: Monitoring
Classifier: Intended Audience :: Developers
Classifier: License :: OSI Approved :: Apache Software License
Classifier: Operating System :: OS Independent
Classifier: Programming Language :: Python
Classifier: Programming Language :: Python :: 2
Classifier: Programming Language :: Python :: 2.7
Classifier: Programming Language :: Python :: 3
Classifier: Programming Language :: Python :: 3.5
Classifier: Programming Language :: Python :: 3.6
Classifier: Programming Language :: Python :: 3.7
Requires-Python: >=2.7, !=3.0.*, !=3.1.*, !=3.2.*, !=3.3.*, !=3.4.*, <4
License-File: LICENSE
License-File: NOTICE
Requires-Dist: grpcio
Requires-Dist: protobuf
Requires-Dist: six
Requires-Dist: cryptography
Provides-Extra: dev
Requires-Dist: grpcio-tools ; extra == 'dev'
Requires-Dist: googleapis-common-protos ; extra == 'dev'
Requires-Dist: pylint ; extra == 'dev'
Requires-Dist: twine ; extra == 'dev'
Requires-Dist: setuptools ; extra == 'dev'
Requires-Dist: wheel ; extra == 'dev'
Requires-Dist: pytest ; extra == 'dev'
Requires-Dist: pytest-cov ; extra == 'dev'
Requires-Dist: pytest-mock ; extra == 'dev'
Requires-Dist: coverage ; extra == 'dev'
